torch_sconce/__init__.py
torch_sconce/sconce.py
torch_sconce-0.0.5.dist-info/LICENSE.txt
torch_sconce-0.0.5.dist-info/METADATA
torch_sconce-0.0.5.dist-info/WHEEL
torch_sconce-0.0.5.dist-info/top_level.txt
torch_sconce-0.0.5.dist-info/RECORD
