Metadata-Version: 2.1
Name: torch-sconce
Version: 0.0.5
Summary: torch_sconce: torch helper
Home-page: https://github.com/satabios/sconce
Download-URL: https://pypi.org/project/torch-sconce/
Author: Sathyaprakash Narayanan
Author-email: snaray17@ucsc.edu
License: MIT
Keywords: Development Pipeline,Deployment Pipeline,Torch,Pruning,Compression,Model Pruning
License-File: LICENSE.txt
